BibliotecaRIT/BibliotecaRITFachada.py
BibliotecaRIT/__init__.py
BibliotecaRIT/Sources/Requisicao.py
BibliotecaRIT/Sources/__init__.py
BibliotecaRIT/Sources/__pycache__/__init__.cpython-310.pyc
BibliotecaRIT/Sources/controladoras/ControladoraCalculoRelevancia.py
BibliotecaRIT/Sources/controladoras/ControladoraExportacaoDados.py
BibliotecaRIT/Sources/controladoras/ControladoraExtracaoDados.py
BibliotecaRIT/Sources/controladoras/ControladoraPreProcessamento.py
BibliotecaRIT/Sources/controladoras/__init__.py
BibliotecaRIT/Sources/entidades/Comentario.py
BibliotecaRIT/Sources/entidades/Projeto.py
BibliotecaRIT/Sources/entidades/Tags.py
BibliotecaRIT/Sources/entidades/Topico.py
BibliotecaRIT/Sources/entidades/__init__.py
BibliotecaRIT/Sources/enums/EnumTag.py
BibliotecaRIT/Sources/enums/__init__.py
BibliotecaRIT/Sources/enums/__pycache__/EnumTag.cpython-310.pyc
BibliotecaRIT/Sources/enums/__pycache__/__init__.cpython-310.pyc
BibliotecaRIT/Sources/estrategias/__init__.py
BibliotecaRIT/Sources/estrategias/__pycache__/__init__.cpython-310.pyc
BibliotecaRIT/Sources/estrategias/exportacao/FiltroExportacaoStrategy.py
BibliotecaRIT/Sources/estrategias/exportacao/VisaoRelevanciaTematicaPorAutor.py
BibliotecaRIT/Sources/estrategias/exportacao/VisaoRelevanciaTematicaPorData.py
BibliotecaRIT/Sources/estrategias/exportacao/VisaoRelevanciaTematicaPorStatus.py
BibliotecaRIT/Sources/estrategias/exportacao/VisaoStrategy.py
BibliotecaRIT/Sources/estrategias/exportacao/__init__.py
BibliotecaRIT/Sources/estrategias/extracao/FiltroExtracaoIssuesAbertas.py
BibliotecaRIT/Sources/estrategias/extracao/FiltroExtracaoIssuesAbertasFechadas.py
BibliotecaRIT/Sources/estrategias/extracao/FiltroExtracaoIssuesFechadas.py
BibliotecaRIT/Sources/estrategias/extracao/FiltroExtracaoStrategy.py
BibliotecaRIT/Sources/estrategias/extracao/__init__.py
BibliotecaRIT/Sources/estrategias/preProcessamento/PreProcessamentoCaminho.py
BibliotecaRIT/Sources/estrategias/preProcessamento/PreProcessamentoCodigoHTML.py
Biblioteca_RIT-3.0.0.dist-info/LICENSE
Biblioteca_RIT-3.0.0.dist-info/METADATA
Biblioteca_RIT-3.0.0.dist-info/WHEEL
Biblioteca_RIT-3.0.0.dist-info/top_level.txt
Biblioteca_RIT-3.0.0.dist-info/RECORD
