Metadata-Version: 2.1
Name: Biblioteca-RIT
Version: 3.0.0
Home-page: https://github.com/BibliotecaRIT/BibliotecaRIT
Author: NuPESSC
Author-email: nupessc@ufv.br
License: MIT License
Keywords: relevância temática,issue tracking,similaridade de cossenos
Classifier: Programming Language :: Python :: 3.10
Classifier: License :: OSI Approved :: MIT License
Classifier: Operating System :: OS Independent
License-File: LICENSE
Requires-Dist: numpy
Requires-Dist: scikit-learn
